{
  "title": "index",
  "images": [
    {
      "image": "/img/zabava_slideshow_2.jpg.webp"
    },
    {
      "image": "/img/slideshow_sport_1.jpg.webp"
    },
    {
      "image": "/img/kultura_slideshow-3.jpg.webp"
    },
    {
      "image": "/img/zabava_slideshow_7.jpg.webp"
    },
    {
      "image": "/img/slideshow_sport_2.jpg.webp"
    },
    {
      "image": "/img/kultura_slideshow-4.jpg.webp"
    },
    {
      "image": "/img/zabava_slideshow_1.jpg.webp"
    },
    {
      "image": "/img/slideshow_sport_3.jpg.webp"
    },
    {
      "image": "/img/kultura_slideshow-1.jpg.webp"
    },
    {
      "image": "/img/zabava_slideshow_6.jpg.webp"
    },
    {
      "image": "/img/slideshow_sport_5.jpg.webp"
    },
    {
      "image": "/img/kultura_slideshow-2.jpg.webp"
    },
    {
      "image": "/img/zabava_slideshow_4.jpg.webp"
    },
    {
      "image": "/img/slideshow_sport_7.jpg.webp"
    },
    {
      "image": "/img/kultura_slideshow-6.jpg.webp"
    },
    {
      "image": "/img/slideshow_sport_4.jpg.webp"
    },
    {
      "image": "/img/slideshow_sport_6.jpg.webp"
    },
    {
      "image": "/img/kultura_slideshow-5.jpg.webp"
    },
    {
      "image": "/img/zabava_slideshow_8.jpg.webp"
    },
    {
      "image": "/img/slideshow_sport_8.jpg.webp"
    },
    {
      "image": "/img/kultura_slideshow-7.jpg.webp"
    },
    {
      "image": "/img/kultura_slideshow-8.jpg.webp"
    }
  ]
}